chordspy/__init__.py
chordspy/app.py
chordspy/beetle.py
chordspy/chords_ble.py
chordspy/chords_serial.py
chordspy/chords_wifi.py
chordspy/connection.py
chordspy/csvplotter.py
chordspy/emgenvelope.py
chordspy/eog.py
chordspy/ffteeg.py
chordspy/game.py
chordspy/gui.py
chordspy/heartbeat_ecg.py
chordspy/keystroke.py
chordspy/config/apps.yaml
chordspy/static/script.js
chordspy/templates/index.html
chordspy-0.1.0.dist-info/licenses/LICENSE
chordspy-0.1.0.dist-info/METADATA
chordspy-0.1.0.dist-info/WHEEL
chordspy-0.1.0.dist-info/entry_points.txt
chordspy-0.1.0.dist-info/top_level.txt
chordspy-0.1.0.dist-info/RECORD
