Metadata-Version: 2.4
Name: chordspy
Version: 0.1.0
Summary: An open source bag of tools for recording and visualizing Bio-potential signals like EEG, ECG, EMG , or EOG.
Home-page: https://github.com/upsidedownlabs/Chords-Python
Author: Payal
Author-email: payallakra307@gmail.com
Classifier: Programming Language :: Python :: 3
Classifier: License :: OSI Approved :: MIT License
Classifier: Operating System :: OS Independent
Requires-Python: >=3.9
License-File: LICENSE
Requires-Dist: numpy==2.1.3
Requires-Dist: pylsl==1.16.2
Requires-Dist: pyserial==3.5
Requires-Dist: bleak==0.22.3
Requires-Dist: pyqtgraph==0.13.7
Requires-Dist: PyQt5==5.15.11
Requires-Dist: keyboard==0.13.5
Requires-Dist: scipy==1.14.1
Requires-Dist: pygame==2.6.1
Requires-Dist: neurokit2==0.2.10
Requires-Dist: plotly==5.24.1
Requires-Dist: pandas==2.2.3
Requires-Dist: tk==0.1.0
Requires-Dist: PyAutoGUI==0.9.54
Requires-Dist: Flask==3.1.1
Requires-Dist: psutil==6.1.1
Requires-Dist: websocket-client==1.8.0
Requires-Dist: PyYAML==6.0.2
Dynamic: author
Dynamic: author-email
Dynamic: classifier
Dynamic: description
Dynamic: description-content-type
Dynamic: home-page
Dynamic: license-file
Dynamic: requires-dist
Dynamic: requires-python
Dynamic: summary
